watchmen_storage_oss/__init__.py
watchmen_storage_oss/data_source_oss.py
watchmen_storage_oss/object_defs_oss.py
watchmen_storage_oss/object_storage_service.py
watchmen_storage_oss/storage_oss.py
watchmen_storage_oss/storage_oss_configuration.py
watchmen_storage_oss-18.0.1.dist-info/METADATA
watchmen_storage_oss-18.0.1.dist-info/WHEEL
watchmen_storage_oss-18.0.1.dist-info/licenses/LICENSE
watchmen_storage_oss-18.0.1.dist-info/RECORD
